<?xml version="1.0" encoding="UTF-8"?>
<!DOCTYPE mapper PUBLIC "-//mybatis.org//DTD Mapper 3.0//EN" "http://mybatis.org/dtd/mybatis-3-mapper.dtd">
<mapper namespace="com.yyw.community.mycommunity.mapper.MessageExtMapper">
    <resultMap id="BaseResultMap" type="com.yyw.community.mycommunity.entity.Message">
        <!--
          WARNING - @mbg.generated
          This element is automatically generated by MyBatis Generator, do not modify.
          This element was generated on Fri Jul 22 02:20:54 CST 2022.
        -->
        <id column="id" jdbcType="BIGINT" property="id" />
        <result column="creator" jdbcType="BIGINT" property="creator" />
        <result column="receiver" jdbcType="BIGINT" property="receiver" />
        <result column="content" jdbcType="VARCHAR" property="content" />
        <result column="status" jdbcType="INTEGER" property="status" />
        <result column="gmt_create" jdbcType="BIGINT" property="gmtCreate" />
    </resultMap>

    <select id="selectMessages" resultMap="BaseResultMap">
        select * from t_message where (creator = #{id1} and receiver = #{id2})
                                 or (receiver = #{id1} and creator = #{id2})
    </select>
</mapper>